{
  "indexes": [
    {
      "collectionGroup": "projects",
      "queryScope": "COLLECTION",
      "fields": [
        { "fieldPath": "tenantId", "order": "ASCENDING" },
        { "fieldPath": "ownerUid", "order": "ASCENDING" },
        { "fieldPath": "status", "order": "ASCENDING" },
        { "fieldPath": "endDate", "order": "ASCENDING" }
      ]
    },
    {
      "collectionGroup": "donors",
      "queryScope": "COLLECTION",
      "fields": [
        { "fieldPath": "tenantId", "order": "ASCENDING" },
        { "fieldPath": "ownerUid", "order": "ASCENDING" },
        { "fieldPath": "hasMissingPhone", "order": "ASCENDING" },
        { "fieldPath": "lastName", "order": "ASCENDING" }
      ]
    },
    {
      "collectionGroup": "donations",
      "queryScope": "COLLECTION",
      "fields": [
        { "fieldPath": "tenantId", "order": "ASCENDING" },
        { "fieldPath": "projectId", "order": "ASCENDING" },
        { "fieldPath": "status", "order": "ASCENDING" },
        { "fieldPath": "donatedAt", "order": "DESCENDING" }
      ]
    },
    {
      "collectionGroup": "payment_promises",
      "queryScope": "COLLECTION",
      "fields": [
        { "fieldPath": "tenantId", "order": "ASCENDING" },
        { "fieldPath": "ownerUid", "order": "ASCENDING" },
        { "fieldPath": "status", "order": "ASCENDING" },
        { "fieldPath": "dueAt", "order": "ASCENDING" }
      ]
    },
    {
      "collectionGroup": "audit_logs",
      "queryScope": "COLLECTION",
      "fields": [
        { "fieldPath": "tenantId", "order": "ASCENDING" },
        { "fieldPath": "actorUid", "order": "ASCENDING" },
        { "fieldPath": "createdAt", "order": "DESCENDING" }
      ]
    }
  ],
  "fieldOverrides": []
}
